Metadata-Version: 2.1
Name: sweet.web
Version: 0.0.8
Summary: Sweet's web autotest module
Home-page: https://github.com/Sweeterio/web
Author: tonglei
Author-email: tonglei@qq.com
License: UNKNOWN
Platform: UNKNOWN
Classifier: Programming Language :: Python :: 3.9
Classifier: License :: OSI Approved :: MIT License
Classifier: Operating System :: OS Independent
